Metadata-Version: 1.1
Name: tuspyclient
Version: 0.1a1
Summary: A Python client for the tus resumable upload protocol ->  http://tus.io
Home-page: http://github.com/ifedapoolarewaju/tus-py-client/
Author: Ifedapo Olarewaju
Author-email: ifedapoolarewaju@gmail.com
License: MIT
Platform: any
Classifier: Programming Language :: Python
Classifier: Natural Language :: English
Classifier: Environment :: Web Environment
Classifier: Intended Audience :: Developers
Classifier: Development Status :: 3 - Alpha
Classifier: License :: OSI Approved :: MIT License
Classifier: Operating System :: OS Independent
Classifier: Topic :: Software Development :: Libraries :: Python Modules
Classifier: Topic :: Internet :: File Transfer Protocol (FTP)
Classifier: Topic :: Communications :: File Sharing
